Tdrn/__init__.py
Tdrn/creat.py
Tdrn/tdrn.py
Tdrn-0.0.1.dist-info/METADATA
Tdrn-0.0.1.dist-info/WHEEL
Tdrn-0.0.1.dist-info/top_level.txt
Tdrn-0.0.1.dist-info/RECORD
