Metadata-Version: 2.1
Name: Tdrn
Version: 0.0.1
Summary: Make a to-do record notebook
Home-page: https://github.com/ditisrmel/Tdrn
Author: Cheng
Author-email: kimichen2907@gmail.com
License: MIT license
Requires-Python: >=3.11.4
